travelperk_http_python/__init__.py
travelperk_http_python/api/__init__.py
travelperk_http_python/api/cost_centers_api.py
travelperk_http_python/api/expenses_api.py
travelperk_http_python/api/greenperk_api.py
travelperk_http_python/api/scim_api.py
travelperk_http_python/api/travelperk.py
travelperk_http_python/api/travelsafe_api.py
travelperk_http_python/api/trips_api.py
travelperk_http_python/api/users_api.py
travelperk_http_python/api/webhooks_api.py
travelperk_http_python/builder/__init__.py
travelperk_http_python/builder/builder.py
travelperk_http_python/client/__init__.py
travelperk_http_python/client/client.py
travelperk_http_python/cost_centers/__init__.py
travelperk_http_python/cost_centers/bulk_update_cost_center_input_params.py
travelperk_http_python/cost_centers/bulk_update_cost_center_request.py
travelperk_http_python/cost_centers/cost_centers.py
travelperk_http_python/cost_centers/create_cost_center_input_params.py
travelperk_http_python/cost_centers/set_users_for_cost_center_input_params.py
travelperk_http_python/cost_centers/set_users_for_cost_center_request.py
travelperk_http_python/cost_centers/update_cost_center_input_params.py
travelperk_http_python/cost_centers/update_cost_center_request.py
travelperk_http_python/exceptions/__init__.py
travelperk_http_python/exceptions/travelperk_http_exception.py
travelperk_http_python/expenses/__init__.py
travelperk_http_python/expenses/billing_period.py
travelperk_http_python/expenses/invoice_lines_input_params.py
travelperk_http_python/expenses/invoice_lines_query.py
travelperk_http_python/expenses/invoice_profiles.py
travelperk_http_python/expenses/invoice_profiles_input_params.py
travelperk_http_python/expenses/invoice_profiles_query.py
travelperk_http_python/expenses/invoices.py
travelperk_http_python/expenses/invoices_input_params.py
travelperk_http_python/expenses/invoices_query.py
travelperk_http_python/expenses/sorting.py
travelperk_http_python/expenses/status.py
travelperk_http_python-1.2.2.dist-info/LICENSE
travelperk_http_python-1.2.2.dist-info/METADATA
travelperk_http_python-1.2.2.dist-info/WHEEL
travelperk_http_python-1.2.2.dist-info/top_level.txt
travelperk_http_python-1.2.2.dist-info/RECORD
