Metadata-Version: 2.1
Name: travelperk-http-python
Version: 1.2.2
Summary: Python SDK for accessing the TravelPerk API 
Home-page: https://github.com/namelivia/travelperk-http-python
Author: José Ignacio Amelivia Santiago
Author-email: jignacio.amelivia@gmail.com
Project-URL: Bug Reports, https://github.com/namelivia/travelperk-http-python/issues
Keywords: travelperk,api
Classifier: Development Status :: 5 - Production/Stable
Classifier: Intended Audience :: Developers
Classifier: Topic :: Software Development :: Build Tools
Classifier: License :: OSI Approved :: MIT License
Classifier: Programming Language :: Python :: 3.8
Classifier: Programming Language :: Python :: 3.9
Requires-Python: >=3.8, <4
License-File: LICENSE
Requires-Dist: travelperk-python-api-types
Requires-Dist: requests
Requires-Dist: requests-oauthlib
Requires-Dist: pyhumps
Requires-Dist: dataclass-map-and-log (==0.1.2)
